mount_azure_blob.py
mount_azure_blob-0.0.7.dist-info/METADATA
mount_azure_blob-0.0.7.dist-info/WHEEL
mount_azure_blob-0.0.7.dist-info/top_level.txt
mount_azure_blob-0.0.7.dist-info/RECORD
