Metadata-Version: 2.1
Name: mount-azure-blob
Version: 0.0.7
Summary: Mount Azure blob storage in google colab.
Home-page: https://github.com/lkarjun/mount-azure-blob-storage/
Author: Lalkrishna
Requires-Python: >=3.7
Requires-Dist: ipywidgets
Requires-Dist: python-dotenv
